buscarProdutos/__init__.py
buscarProdutos/buscarNaMagalu.py
buscarProdutos/buscarNoMercadoLivre.py
buscarProdutos-0.3.3.dist-info/METADATA
buscarProdutos-0.3.3.dist-info/WHEEL
buscarProdutos-0.3.3.dist-info/top_level.txt
buscarProdutos-0.3.3.dist-info/RECORD
