Metadata-Version: 2.1
Name: buscarProdutos
Version: 0.3.3
Summary: Busca produtos na web
Author: Alison
Author-email: alissonmarqueshm30@gmail.com
Keywords: python,busca,web,produto,preço,mercado livre,magazine luiza
Classifier: Development Status :: 3 - Alpha
Classifier: Intended Audience :: Developers
Classifier: Programming Language :: Python :: 3
Classifier: Operating System :: OS Independent
Requires-Dist: beautifulsoup4
Requires-Dist: requests
